{
  "destination": [
    {
      "schedule_interval": "*/5 * * * * *",
      "url": "google.com",
      "port": "80",
      "id": 1594136624527
    },
    {
      "schedule_interval": "*/5 * * * * *",
      "url": "google.com",
      "port": "443",
      "id": 1594324053993
    },
    {
      "schedule_interval": "*/10 * * * * *",
      "url": "amazon.com",
      "port": "80",
      "id": 1594340305294
    },
    {
      "schedule_interval": "*/5 * * * * *",
      "url": "blizzard.com",
      "port": "443",
      "id": 1594342125147
    }
  ]
}